bendihua/__init__.py
bendihua/_version.py
bendihua/main.py
bendihua-0.0.2.dist-info/DESCRIPTION.rst
bendihua-0.0.2.dist-info/METADATA
bendihua-0.0.2.dist-info/RECORD
bendihua-0.0.2.dist-info/WHEEL
bendihua-0.0.2.dist-info/entry_points.txt
bendihua-0.0.2.dist-info/metadata.json
bendihua-0.0.2.dist-info/top_level.txt
fanyi/__init__.py
fanyi/_version.py
fanyi/main.py
