Metadata-Version: 2.0
Name: bendihua
Version: 0.0.2
Summary: googletrans command line interface to translate your i18n file into 106 languages
Home-page: https://github.com/chfw/bendihua
Author: C.W.
Author-email: wangc_2011@hotmail.com
License: MIT
Download-URL: https://github.com/chfw/bendihua/archive/0.0.2.tar.gz
Keywords: python
Platform: UNKNOWN
Classifier: Topic :: Office/Business
Classifier: Topic :: Utilities
Classifier: Topic :: Software Development :: Libraries
Classifier: Programming Language :: Python
Classifier: Intended Audience :: Developers
Classifier: Programming Language :: Python :: 2.6
Classifier: Programming Language :: Python :: 2.7
Classifier: Programming Language :: Python :: 3.3
Classifier: Programming Language :: Python :: 3.4
Classifier: Programming Language :: Python :: 3.5
Classifier: Programming Language :: Python :: 3.6
Requires-Dist: googletrans
